ll_oscilloscope_measurements.py
ll_oscilloscope_measurements-0.1.1.dist-info/LICENSE
ll_oscilloscope_measurements-0.1.1.dist-info/METADATA
ll_oscilloscope_measurements-0.1.1.dist-info/WHEEL
ll_oscilloscope_measurements-0.1.1.dist-info/top_level.txt
ll_oscilloscope_measurements-0.1.1.dist-info/RECORD
